pyworld_fixed-0.3.8.dist-info/METADATA
pyworld_fixed-0.3.8.dist-info/LICENSE
pyworld_fixed-0.3.8.dist-info/RECORD
pyworld_fixed-0.3.8.dist-info/WHEEL
pyworld_fixed-0.3.8.dist-info/top_level.txt
pyworld/pyworld.cpython-312-x86_64-linux-gnu.so
pyworld/__init__.py
