Metadata-Version: 2.1
Name: pyworld-fixed
Version: 0.3.8
Summary: PyWorld: a Python wrapper for WORLD vocoder -- Now supporting Python 3.12
Home-page: https://github.com/JackismyShephard/Python-Wrapper-for-World-Vocoder
Author: Pyworld Contributors
Author-email: jackismyshephard@gmail.com
Keywords: vocoder
License-File: LICENSE
Requires-Dist: numpy
Requires-Dist: cython>=0.24
Provides-Extra: sdist
Requires-Dist: numpy; extra == "sdist"
Requires-Dist: cython>=0.24; extra == "sdist"
Provides-Extra: test
Requires-Dist: nose; extra == "test"
